line_notifier/__init__.py
line_notifier/notifier.py
line_notifier/ui_manager.py
LINE_Notifier_YuuoS-1.1.0.dist-info/LICENSE
LINE_Notifier_YuuoS-1.1.0.dist-info/METADATA
LINE_Notifier_YuuoS-1.1.0.dist-info/WHEEL
LINE_Notifier_YuuoS-1.1.0.dist-info/top_level.txt
LINE_Notifier_YuuoS-1.1.0.dist-info/RECORD
