Metadata-Version: 2.1
Name: LINE_Notifier_YuuoS
Version: 1.1.0
Summary: LINE notifier for our laser machines
Home-page: https://github.com/YuuoS/YamalabLaserPackage/tree/main/notifier
Author: Yuki Oshima
Author-email: Yuki Oshima <05.pistes.respect@icloud.com>
Project-URL: Homepage, https://github.com/YuuoS/YamalabLaserPackage/tree/main/notifier
Project-URL: Issues, https://github.com/YuuoS/YamalabLaserPackage/tree/main/notifier/issues
Keywords: notification,UI,tkinter
Classifier: Programming Language :: Python :: 3
Classifier: License :: OSI Approved :: MIT License
Classifier: Operating System :: OS Independent
Requires-Python: >=3.6
License-File: LICENSE
Requires-Dist: requests
Requires-Dist: pyperclip
